{
  "slug": "the-mindskinner",
  "cards": [
    {
      "name": "The Mindskinner",
      "percent": null,
      "deckCount": null,
      "synergy": null
    },
    {
      "name": "The Water Crystal",
      "percent": 56,
      "deckCount": 1469,
      "synergy": 45
    },
    {
      "name": "Jidoor, Aristocratic Capital",
      "percent": 31,
      "deckCount": 1630,
      "synergy": 26
    },
    {
      "name": "Genji Glove",
      "percent": 17,
      "deckCount": 1250,
      "synergy": 16
    },
    {
      "name": "Magic Damper",
      "percent": 5,
      "deckCount": 1300,
      "synergy": 3
    },
    {
      "name": "Gogo, Master of Mimicry",
      "percent": 3,
      "deckCount": 1388,
      "synergy": 0
    },
    {
      "name": "Fractured Sanity",
      "percent": 72,
      "deckCount": 7136,
      "synergy": 65
    },
    {
      "name": "Ruin Crab",
      "percent": 73,
      "deckCount": 7136,
      "synergy": 65
    },
    {
      "name": "Fireshrieker",
      "percent": 70,
      "deckCount": 7136,
      "synergy": 64
    },
    {
      "name": "Bruvac the Grandiloquent",
      "percent": 67,
      "deckCount": 7136,
      "synergy": 64
    },
    {
      "name": "Maddening Cacophony",
      "percent": 70,
      "deckCount": 7136,
      "synergy": 63
    },
    {
      "name": "Bonehoard",
      "percent": 56,
      "deckCount": 7136,
      "synergy": 54
    },
    {
      "name": "Tasha's Hideous Laughter",
      "percent": 56,
      "deckCount": 7136,
      "synergy": 51
    },
    {
      "name": "Jace's Phantasm",
      "percent": 55,
      "deckCount": 7136,
      "synergy": 51
    },
    {
      "name": "Terisian Mindbreaker",
      "percent": 55,
      "deckCount": 7136,
      "synergy": 50
    },
    {
      "name": "Fraying Sanity",
      "percent": 53,
      "deckCount": 7136,
      "synergy": 49
    },
    {
      "name": "Swiftfoot Boots",
      "percent": 72,
      "deckCount": 7136,
      "synergy": 44
    },
    {
      "name": "Counterspell",
      "percent": 72,
      "deckCount": 7136,
      "synergy": 4
    },
    {
      "name": "Propaganda",
      "percent": 66,
      "deckCount": 7136,
      "synergy": 38
    },
    {
      "name": "Sapphire Medallion",
      "percent": 64,
      "deckCount": 7136,
      "synergy": 9
    },
    {
      "name": "Lightning Greaves",
      "percent": 55,
      "deckCount": 7136,
      "synergy": 29
    },
    {
      "name": "Blackblade Reforged",
      "percent": 52,
      "deckCount": 7136,
      "synergy": 47
    },
    {
      "name": "Psychic Corrosion",
      "percent": 52,
      "deckCount": 7136,
      "synergy": 44
    },
    {
      "name": "Memory Erosion",
      "percent": 51,
      "deckCount": 7136,
      "synergy": 46
    },
    {
      "name": "Undead Alchemist",
      "percent": 50,
      "deckCount": 7136,
      "synergy": 47
    },
    {
      "name": "Negate",
      "percent": 47,
      "deckCount": 7136,
      "synergy": 8
    },
    {
      "name": "Rhystic Study",
      "percent": null,
      "deckCount": null,
      "synergy": null
    },
    {
      "name": "Cyclonic Rift",
      "percent": null,
      "deckCount": null,
      "synergy": null
    },
    {
      "name": "Fierce Guardianship",
      "percent": null,
      "deckCount": null,
      "synergy": null
    },
    {
      "name": "Mystical Tutor",
      "percent": null,
      "deckCount": null,
      "synergy": null
    },
    {
      "name": "Force of Will",
      "percent": null,
      "deckCount": null,
      "synergy": null
    },
    {
      "name": "Consecrated Sphinx",
      "percent": null,
      "deckCount": null,
      "synergy": null
    },
    {
      "name": "The One Ring",
      "percent": null,
      "deckCount": null,
      "synergy": null
    },
    {
      "name": "Ancient Tomb",
      "percent": null,
      "deckCount": null,
      "synergy": null
    },
    {
      "name": "Spark Double",
      "percent": 45,
      "deckCount": 7136,
      "synergy": 31
    },
    {
      "name": "Fleet Swallower",
      "percent": 45,
      "deckCount": 7136,
      "synergy": 41
    },
    {
      "name": "Zellix, Sanity Flayer",
      "percent": 45,
      "deckCount": 7136,
      "synergy": 42
    },
    {
      "name": "Soulless Jailer",
      "percent": 43,
      "deckCount": 7136,
      "synergy": 40
    },
    {
      "name": "Hedron Crab",
      "percent": 41,
      "deckCount": 7136,
      "synergy": 36
    },
    {
      "name": "Vantress Gargoyle",
      "percent": 38,
      "deckCount": 7136,
      "synergy": 36
    },
    {
      "name": "Auton Soldier",
      "percent": 34,
      "deckCount": 7136,
      "synergy": 30
    },
    {
      "name": "Silent Hallcreeper",
      "percent": 33,
      "deckCount": 7136,
      "synergy": 28
    },
    {
      "name": "Giggling Skitterspike",
      "percent": 33,
      "deckCount": 7136,
      "synergy": 30
    },
    {
      "name": "Mirelurk Queen",
      "percent": 30,
      "deckCount": 7136,
      "synergy": 27
    },
    {
      "name": "Eluge, the Shoreless Sea",
      "percent": 29,
      "deckCount": 7136,
      "synergy": 20
    },
    {
      "name": "Esior, Wardwing Familiar",
      "percent": 29,
      "deckCount": 7136,
      "synergy": 26
    },
    {
      "name": "Solemn Simulacrum",
      "percent": 28,
      "deckCount": 7136,
      "synergy": 5
    },
    {
      "name": "Riddlekeeper",
      "percent": 26,
      "deckCount": 7136,
      "synergy": 24
    },
    {
      "name": "Dreamborn Muse",
      "percent": 25,
      "deckCount": 7136,
      "synergy": 22
    },
    {
      "name": "Sakashima of a Thousand Faces",
      "percent": 24,
      "deckCount": 7136,
      "synergy": 17
    },
    {
      "name": "Shadow Kin",
      "percent": 21,
      "deckCount": 7136,
      "synergy": 19
    },
    {
      "name": "Tempest Djinn",
      "percent": 21,
      "deckCount": 7136,
      "synergy": 19
    },
    {
      "name": "Fog Bank",
      "percent": 20,
      "deckCount": 7136,
      "synergy": 17
    },
    {
      "name": "Hydroelectric Specimen",
      "percent": 18,
      "deckCount": 7136,
      "synergy": 5
    },
    {
      "name": "Relic Golem",
      "percent": 18,
      "deckCount": 7136,
      "synergy": 17
    },
    {
      "name": "Canoptek Scarab Swarm",
      "percent": 17,
      "deckCount": 7136,
      "synergy": 16
    },
    {
      "name": "Defiler of Dreams",
      "percent": 17,
      "deckCount": 7136,
      "synergy": 7
    },
    {
      "name": "Manic Scribe",
      "percent": 16,
      "deckCount": 7136,
      "synergy": 15
    },
    {
      "name": "Charix, the Raging Isle",
      "percent": 15,
      "deckCount": 7136,
      "synergy": 12
    },
    {
      "name": "Harbinger of the Seas",
      "percent": 15,
      "deckCount": 7136,
      "synergy": 5
    },
    {
      "name": "Brass Squire",
      "percent": 15,
      "deckCount": 7136,
      "synergy": 13
    },
    {
      "name": "Faerie Mastermind",
      "percent": 14,
      "deckCount": 7136,
      "synergy": 1
    },
    {
      "name": "Siren Stormtamer",
      "percent": 14,
      "deckCount": 7136,
      "synergy": 7
    },
    {
      "name": "Spellskite",
      "percent": 13,
      "deckCount": 7136,
      "synergy": 3
    },
    {
      "name": "Deepmuck Desperado",
      "percent": 13,
      "deckCount": 7136,
      "synergy": 12
    },
    {
      "name": "Silent Arbiter",
      "percent": 12,
      "deckCount": 7136,
      "synergy": 8
    },
    {
      "name": "Hullbreaker Horror",
      "percent": null,
      "deckCount": null,
      "synergy": null
    },
    {
      "name": "Sphinx Mindbreaker",
      "percent": 11,
      "deckCount": 7136,
      "synergy": 10
    },
    {
      "name": "Jace's Archivist",
      "percent": 11,
      "deckCount": 7136,
      "synergy": 7
    },
    {
      "name": "Sakashima the Impostor",
      "percent": 11,
      "deckCount": 7136,
      "synergy": 8
    },
    {
      "name": "Stuffy Doll",
      "percent": 11,
      "deckCount": 7136,
      "synergy": 11
    },
    {
      "name": "Scourge of Fleets",
      "percent": null,
      "deckCount": null,
      "synergy": null
    },
    {
      "name": "Diluvian Primordial",
      "percent": 10,
      "deckCount": 7136,
      "synergy": 7
    },
    {
      "name": "Silver Myr",
      "percent": null,
      "deckCount": null,
      "synergy": null
    },
    {
      "name": "Overlord of the Floodpits",
      "percent": 10,
      "deckCount": 7136,
      "synergy": 7
    },
    {
      "name": "Body of Knowledge",
      "percent": 9,
      "deckCount": 7136,
      "synergy": 3
    },
    {
      "name": "Phyrexian Metamorph",
      "percent": null,
      "deckCount": null,
      "synergy": null
    },
    {
      "name": "Chasm Skulker",
      "percent": null,
      "deckCount": null,
      "synergy": null
    },
    {
      "name": "Kiora, the Rising Tide",
      "percent": 8,
      "deckCount": 5274,
      "synergy": 4
    },
    {
      "name": "Thassa, God of the Sea",
      "percent": 7,
      "deckCount": 7136,
      "synergy": 4
    },
    {
      "name": "Veteran Ice Climber",
      "percent": 7,
      "deckCount": 2406,
      "synergy": 6
    },
    {
      "name": "Etherium Sculptor",
      "percent": null,
      "deckCount": null,
      "synergy": null
    },
    {
      "name": "Trophy Mage",
      "percent": null,
      "deckCount": null,
      "synergy": null
    },
    {
      "name": "Fear of Impostors",
      "percent": 7,
      "deckCount": 7136,
      "synergy": 5
    },
    {
      "name": "Aetherize",
      "percent": 46,
      "deckCount": 7136,
      "synergy": 19
    },
    {
      "name": "Visions of Beyond",
      "percent": 45,
      "deckCount": 7136,
      "synergy": 39
    },
    {
      "name": "Arcane Denial",
      "percent": 44,
      "deckCount": 7136,
      "synergy": 9
    },
    {
      "name": "Pongify",
      "percent": 42,
      "deckCount": 7136,
      "synergy": 1
    },
    {
      "name": "Didn't Say Please",
      "percent": 42,
      "deckCount": 7136,
      "synergy": 37
    },
    {
      "name": "High Tide",
      "percent": null,
      "deckCount": null,
      "synergy": null
    },
    {
      "name": "An Offer You Can't Refuse",
      "percent": 38,
      "deckCount": 7136,
      "synergy": 3
    },
    {
      "name": "Rapid Hybridization",
      "percent": null,
      "deckCount": null,
      "synergy": null
    },
    {
      "name": "Thought Collapse",
      "percent": 34,
      "deckCount": 7136,
      "synergy": 31
    },
    {
      "name": "Drown in Dreams",
      "percent": 33,
      "deckCount": 7136,
      "synergy": 28
    },
    {
      "name": "Slip Out the Back",
      "percent": 32,
      "deckCount": 7136,
      "synergy": 24
    },
    {
      "name": "Archive Trap",
      "percent": 30,
      "deckCount": 7136,
      "synergy": 27
    },
    {
      "name": "Thought Scour",
      "percent": 28,
      "deckCount": 7136,
      "synergy": 20
    },
    {
      "name": "Brainstorm",
      "percent": null,
      "deckCount": null,
      "synergy": null
    },
    {
      "name": "Reality Shift",
      "percent": null,
      "deckCount": null,
      "synergy": null
    },
    {
      "name": "Mana Drain",
      "percent": null,
      "deckCount": null,
      "synergy": null
    },
    {
      "name": "Frantic Search",
      "percent": null,
      "deckCount": null,
      "synergy": null
    },
    {
      "name": "Into the Story",
      "percent": 21,
      "deckCount": 7136,
      "synergy": 19
    },
    {
      "name": "Swan Song",
      "percent": null,
      "deckCount": null,
      "synergy": null
    },
    {
      "name": "Get Out",
      "percent": 18,
      "deckCount": 7072,
      "synergy": 15
    },
    {
      "name": "Stubborn Denial",
      "percent": 17,
      "deckCount": 7136,
      "synergy": 15
    },
    {
      "name": "Sink into Stupor",
      "percent": null,
      "deckCount": null,
      "synergy": null
    },
    {
      "name": "Flow of Knowledge",
      "percent": null,
      "deckCount": null,
      "synergy": null
    },
    {
      "name": "Opt",
      "percent": null,
      "deckCount": null,
      "synergy": null
    },
    {
      "name": "Archmage's Charm",
      "percent": null,
      "deckCount": null,
      "synergy": null
    },
    {
      "name": "Don't Make a Sound",
      "percent": 12,
      "deckCount": 7039,
      "synergy": 10
    },
    {
      "name": "Spell Rupture",
      "percent": 12,
      "deckCount": 7136,
      "synergy": 11
    },
    {
      "name": "Long River's Pull",
      "percent": 12,
      "deckCount": 7136,
      "synergy": 7
    },
    {
      "name": "Reenact the Crime",
      "percent": 11,
      "deckCount": 7136,
      "synergy": 9
    },
    {
      "name": "Resculpt",
      "percent": null,
      "deckCount": null,
      "synergy": null
    },
    {
      "name": "Shore Up",
      "percent": 11,
      "deckCount": 7136,
      "synergy": 6
    },
    {
      "name": "Strix Serenade",
      "percent": null,
      "deckCount": null,
      "synergy": null
    },
    {
      "name": "Aetherspouts",
      "percent": 9,
      "deckCount": 7136,
      "synergy": 2
    },
    {
      "name": "See Double",
      "percent": 9,
      "deckCount": 7136,
      "synergy": 4
    },
    {
      "name": "Three Steps Ahead",
      "percent": null,
      "deckCount": null,
      "synergy": null
    },
    {
      "name": "March of Swirling Mist",
      "percent": null,
      "deckCount": null,
      "synergy": null
    },
    {
      "name": "Force of Negation",
      "percent": null,
      "deckCount": null,
      "synergy": null
    },
    {
      "name": "Refute",
      "percent": 7,
      "deckCount": 5399,
      "synergy": 1
    },
    {
      "name": "Brain Freeze",
      "percent": 6,
      "deckCount": 7136,
      "synergy": 2
    },
    {
      "name": "Psychic Spiral",
      "percent": 6,
      "deckCount": 7136,
      "synergy": 5
    },
    {
      "name": "Countermand",
      "percent": 6,
      "deckCount": 7136,
      "synergy": 5
    },
    {
      "name": "Muddle the Mixture",
      "percent": null,
      "deckCount": null,
      "synergy": null
    },
    {
      "name": "Cyber Conversion",
      "percent": 5,
      "deckCount": 7136,
      "synergy": 1
    },
    {
      "name": "Glimmerburst",
      "percent": 5,
      "deckCount": 7009,
      "synergy": 4
    },
    {
      "name": "Flare of Denial",
      "percent": null,
      "deckCount": null,
      "synergy": null
    },
    {
      "name": "Windfall",
      "percent": 41,
      "deckCount": 7136,
      "synergy": 17
    },
    {
      "name": "Cut Your Losses",
      "percent": 38,
      "deckCount": 7136,
      "synergy": 34
    },
    {
      "name": "Traumatize",
      "percent": 36,
      "deckCount": 7136,
      "synergy": 31
    },
    {
      "name": "Irenicus's Vile Duplication",
      "percent": 33,
      "deckCount": 7136,
      "synergy": 25
    },
    {
      "name": "Ponder",
      "percent": null,
      "deckCount": null,
      "synergy": null
    },
    {
      "name": "Nanogene Conversion",
      "percent": 22,
      "deckCount": 7136,
      "synergy": 20
    },
    {
      "name": "Enter the Enigma",
      "percent": 15,
      "deckCount": 7127,
      "synergy": 8
    },
    {
      "name": "Quantum Misalignment",
      "percent": 15,
      "deckCount": 7136,
      "synergy": 11
    },
    {
      "name": "Fabricate",
      "percent": null,
      "deckCount": null,
      "synergy": null
    },
    {
      "name": "Preordain",
      "percent": null,
      "deckCount": null,
      "synergy": null
    },
    {
      "name": "Mind Sculpt",
      "percent": 13,
      "deckCount": 7136,
      "synergy": 12
    },
    {
      "name": "Sorcerous Squall",
      "percent": 12,
      "deckCount": 7136,
      "synergy": 10
    },
    {
      "name": "Chart a Course",
      "percent": 10,
      "deckCount": 7136,
      "synergy": 5
    },
    {
      "name": "Sea Gate Restoration",
      "percent": null,
      "deckCount": null,
      "synergy": null
    },
    {
      "name": "Increasing Confusion",
      "percent": 8,
      "deckCount": 7136,
      "synergy": 7
    },
    {
      "name": "Treasure Cruise",
      "percent": null,
      "deckCount": null,
      "synergy": null
    },
    {
      "name": "Tome Scour",
      "percent": 8,
      "deckCount": 7136,
      "synergy": 7
    },
    {
      "name": "Ravenform",
      "percent": null,
      "deckCount": null,
      "synergy": null
    },
    {
      "name": "Curse of the Swine",
      "percent": null,
      "deckCount": null,
      "synergy": null
    },
    {
      "name": "Spectral Deluge",
      "percent": null,
      "deckCount": null,
      "synergy": null
    },
    {
      "name": "Mind Bomb",
      "percent": 6,
      "deckCount": 7136,
      "synergy": 6
    },
    {
      "name": "Startled Awake",
      "percent": 6,
      "deckCount": 7136,
      "synergy": 5
    },
    {
      "name": "Lórien Revealed",
      "percent": null,
      "deckCount": null,
      "synergy": null
    },
    {
      "name": "Riverchurn Monument",
      "percent": 38,
      "deckCount": 3688,
      "synergy": 34
    },
    {
      "name": "Mesmeric Orb",
      "percent": 36,
      "deckCount": 7136,
      "synergy": 32
    },
    {
      "name": "Mindcrank",
      "percent": 34,
      "deckCount": 7136,
      "synergy": 30
    },
    {
      "name": "Leyline Axe",
      "percent": 33,
      "deckCount": 5332,
      "synergy": 30
    },
    {
      "name": "Sword of the Animist",
      "percent": 32,
      "deckCount": 7136,
      "synergy": 27
    },
    {
      "name": "Commander's Plate",
      "percent": 28,
      "deckCount": 7136,
      "synergy": 24
    },
    {
      "name": "Helm of the Host",
      "percent": 26,
      "deckCount": 7136,
      "synergy": 23
    },
    {
      "name": "Trepanation Blade",
      "percent": 26,
      "deckCount": 7136,
      "synergy": 25
    },
    {
      "name": "Mithril Coat",
      "percent": 24,
      "deckCount": 7136,
      "synergy": 21
    },
    {
      "name": "Mjölnir, Storm Hammer",
      "percent": 23,
      "deckCount": 7136,
      "synergy": 21
    },
    {
      "name": "Grafdigger's Cage",
      "percent": 22,
      "deckCount": 7136,
      "synergy": 18
    },
    {
      "name": "Champion's Helm",
      "percent": 22,
      "deckCount": 7136,
      "synergy": 20
    },
    {
      "name": "Excalibur, Sword of Eden",
      "percent": 19,
      "deckCount": 7136,
      "synergy": 17
    },
    {
      "name": "Brass Knuckles",
      "percent": 18,
      "deckCount": 7136,
      "synergy": 17
    },
    {
      "name": "Strata Scythe",
      "percent": 17,
      "deckCount": 7136,
      "synergy": 15
    },
    {
      "name": "Hammer of Nazahn",
      "percent": 17,
      "deckCount": 7136,
      "synergy": 15
    },
    {
      "name": "Soul-Guide Lantern",
      "percent": 16,
      "deckCount": 7136,
      "synergy": 12
    },
    {
      "name": "Colossus Hammer",
      "percent": 16,
      "deckCount": 7136,
      "synergy": 15
    },
    {
      "name": "Lavaspur Boots",
      "percent": 15,
      "deckCount": 7136,
      "synergy": 13
    },
    {
      "name": "Wayfarer's Bauble",
      "percent": null,
      "deckCount": null,
      "synergy": null
    },
    {
      "name": "Altar of the Brood",
      "percent": 15,
      "deckCount": 7136,
      "synergy": 11
    },
    {
      "name": "Inquisitor's Flail",
      "percent": 11,
      "deckCount": 7136,
      "synergy": 10
    },
    {
      "name": "Crawlspace",
      "percent": 11,
      "deckCount": 7136,
      "synergy": 8
    },
    {
      "name": "Thran Power Suit",
      "percent": 11,
      "deckCount": 7136,
      "synergy": 10
    },
    {
      "name": "Tormod's Crypt",
      "percent": 10,
      "deckCount": 7136,
      "synergy": 1
    },
    {
      "name": "Nettlecyst",
      "percent": 9,
      "deckCount": 7136,
      "synergy": 7
    },
    {
      "name": "Folio of Fancies",
      "percent": 8,
      "deckCount": 7136,
      "synergy": 4
    },
    {
      "name": "Keening Stone",
      "percent": 8,
      "deckCount": 7136,
      "synergy": 7
    },
    {
      "name": "Grindstone",
      "percent": 8,
      "deckCount": 7136,
      "synergy": 6
    },
    {
      "name": "Winter Moon",
      "percent": 8,
      "deckCount": 7136,
      "synergy": 3
    },
    {
      "name": "Blade of Selves",
      "percent": 8,
      "deckCount": 7136,
      "synergy": 6
    },
    {
      "name": "Winged Boots",
      "percent": 8,
      "deckCount": 7136,
      "synergy": 4
    },
    {
      "name": "Relic of Progenitus",
      "percent": 7,
      "deckCount": 7136,
      "synergy": 6
    },
    {
      "name": "Realmbreaker, the Invasion Tree",
      "percent": 7,
      "deckCount": 7136,
      "synergy": 6
    },
    {
      "name": "Ghost Vacuum",
      "percent": 7,
      "deckCount": 7136,
      "synergy": 6
    },
    {
      "name": "Masterwork of Ingenuity",
      "percent": 7,
      "deckCount": 7136,
      "synergy": 6
    },
    {
      "name": "Darksteel Plate",
      "percent": 7,
      "deckCount": 7136,
      "synergy": 6
    },
    {
      "name": "Assault Suit",
      "percent": 7,
      "deckCount": 7136,
      "synergy": 6
    },
    {
      "name": "Ring of Evos Isle",
      "percent": 7,
      "deckCount": 7136,
      "synergy": 6
    },
    {
      "name": "Bitterthorn, Nissa's Animus",
      "percent": 6,
      "deckCount": 7136,
      "synergy": 5
    },
    {
      "name": "Sword of Body and Mind",
      "percent": 6,
      "deckCount": 7136,
      "synergy": 5
    },
    {
      "name": "Gavel of the Righteous",
      "percent": 5,
      "deckCount": 7136,
      "synergy": 5
    },
    {
      "name": "Whispersilk Cloak",
      "percent": 5,
      "deckCount": 7136,
      "synergy": 3
    },
    {
      "name": "Strength-Testing Hammer",
      "percent": 5,
      "deckCount": 7136,
      "synergy": 5
    },
    {
      "name": "Court of Cunning",
      "percent": 30,
      "deckCount": 7136,
      "synergy": 26
    },
    {
      "name": "Sphinx's Tutelage",
      "percent": 28,
      "deckCount": 7136,
      "synergy": 23
    },
    {
      "name": "Drowned Secrets",
      "percent": 26,
      "deckCount": 7136,
      "synergy": 22
    },
    {
      "name": "Unable to Scream",
      "percent": 25,
      "deckCount": 7136,
      "synergy": 20
    },
    {
      "name": "Imprisoned in the Moon",
      "percent": 20,
      "deckCount": 7136,
      "synergy": 8
    },
    {
      "name": "Teferi's Tutelage",
      "percent": 20,
      "deckCount": 7136,
      "synergy": 16
    },
    {
      "name": "Mystic Remora",
      "percent": null,
      "deckCount": null,
      "synergy": null
    },
    {
      "name": "Eel Umbra",
      "percent": 17,
      "deckCount": 7136,
      "synergy": 15
    },
    {
      "name": "Wizard Class",
      "percent": null,
      "deckCount": null,
      "synergy": null
    },
    {
      "name": "Forced Fruition",
      "percent": 12,
      "deckCount": 7136,
      "synergy": 10
    },
    {
      "name": "Dissipation Field",
      "percent": 12,
      "deckCount": 7136,
      "synergy": 8
    },
    {
      "name": "Struggle for Project Purity",
      "percent": 11,
      "deckCount": 7136,
      "synergy": 9
    },
    {
      "name": "Witness Protection",
      "percent": 9,
      "deckCount": 7136,
      "synergy": 3
    },
    {
      "name": "Jace's Erasure",
      "percent": 8,
      "deckCount": 7136,
      "synergy": 6
    },
    {
      "name": "Amphibian Downpour",
      "percent": 8,
      "deckCount": 7136,
      "synergy": 2
    },
    {
      "name": "Nerd Rage",
      "percent": 8,
      "deckCount": 7136,
      "synergy": 4
    },
    {
      "name": "Back to Basics",
      "percent": null,
      "deckCount": null,
      "synergy": null
    },
    {
      "name": "Patient Rebuilding",
      "percent": 7,
      "deckCount": 7136,
      "synergy": 6
    },
    {
      "name": "Eldrazi Conscription",
      "percent": 6,
      "deckCount": 7136,
      "synergy": 5
    },
    {
      "name": "Mirrormade",
      "percent": 6,
      "deckCount": 7136,
      "synergy": 1
    },
    {
      "name": "Unstoppable Plan",
      "percent": null,
      "deckCount": null,
      "synergy": null
    },
    {
      "name": "Jace, the Perfected Mind",
      "percent": 24,
      "deckCount": 7136,
      "synergy": 20
    },
    {
      "name": "Jace, Memory Adept",
      "percent": 16,
      "deckCount": 7136,
      "synergy": 13
    },
    {
      "name": "Jace Beleren",
      "percent": 8,
      "deckCount": 7136,
      "synergy": 5
    },
    {
      "name": "Jace, Wielder of Mysteries",
      "percent": null,
      "deckCount": null,
      "synergy": null
    },
    {
      "name": "Mystic Sanctuary",
      "percent": null,
      "deckCount": null,
      "synergy": null
    },
    {
      "name": "Reliquary Tower",
      "percent": null,
      "deckCount": null,
      "synergy": null
    },
    {
      "name": "Scavenger Grounds",
      "percent": 33,
      "deckCount": 7136,
      "synergy": 26
    },
    {
      "name": "Nykthos, Shrine to Nyx",
      "percent": 24,
      "deckCount": 7136,
      "synergy": 8
    },
    {
      "name": "War Room",
      "percent": 22,
      "deckCount": 7136,
      "synergy": 5
    },
    {
      "name": "Rogue's Passage",
      "percent": 21,
      "deckCount": 7136,
      "synergy": 6
    },
    {
      "name": "Otawara, Soaring City",
      "percent": null,
      "deckCount": null,
      "synergy": null
    },
    {
      "name": "Castle Vantress",
      "percent": null,
      "deckCount": null,
      "synergy": null
    },
    {
      "name": "Academy Ruins",
      "percent": null,
      "deckCount": null,
      "synergy": null
    },
    {
      "name": "Archway of Innovation",
      "percent": 14,
      "deckCount": 7136,
      "synergy": 3
    },
    {
      "name": "Temple of the False God",
      "percent": 11,
      "deckCount": 7136,
      "synergy": 0
    },
    {
      "name": "Maze of Ith",
      "percent": 10,
      "deckCount": 7136,
      "synergy": 5
    },
    {
      "name": "Rivendell",
      "percent": null,
      "deckCount": null,
      "synergy": null
    },
    {
      "name": "Urza's Saga",
      "percent": null,
      "deckCount": null,
      "synergy": null
    },
    {
      "name": "Halimar Depths",
      "percent": null,
      "deckCount": null,
      "synergy": null
    },
    {
      "name": "Mistrise Village",
      "percent": null,
      "deckCount": null,
      "synergy": null
    },
    {
      "name": "Sunken Palace",
      "percent": 8,
      "deckCount": 7136,
      "synergy": 3
    },
    {
      "name": "Minamo, School at Water's Edge",
      "percent": null,
      "deckCount": null,
      "synergy": null
    },
    {
      "name": "Lonely Sandbar",
      "percent": null,
      "deckCount": null,
      "synergy": null
    },
    {
      "name": "Buried Ruin",
      "percent": null,
      "deckCount": null,
      "synergy": null
    },
    {
      "name": "Geier Reach Sanitarium",
      "percent": 6,
      "deckCount": 7136,
      "synergy": 2
    },
    {
      "name": "Bonders' Enclave",
      "percent": 6,
      "deckCount": 7136,
      "synergy": 4
    },
    {
      "name": "Mikokoro, Center of the Sea",
      "percent": 5,
      "deckCount": 7136,
      "synergy": 1
    },
    {
      "name": "Terrain Generator",
      "percent": null,
      "deckCount": null,
      "synergy": null
    },
    {
      "name": "Sol Ring",
      "percent": null,
      "deckCount": null,
      "synergy": null
    },
    {
      "name": "Arcane Signet",
      "percent": 70,
      "deckCount": 7136,
      "synergy": 4
    },
    {
      "name": "Thought Vessel",
      "percent": null,
      "deckCount": null,
      "synergy": null
    },
    {
      "name": "Sky Diamond",
      "percent": 29,
      "deckCount": 7136,
      "synergy": 4
    },
    {
      "name": "Midnight Clock",
      "percent": 27,
      "deckCount": 7136,
      "synergy": 6
    },
    {
      "name": "Mind Stone",
      "percent": null,
      "deckCount": null,
      "synergy": null
    },
    {
      "name": "Fellwar Stone",
      "percent": null,
      "deckCount": null,
      "synergy": null
    },
    {
      "name": "Throne of Eldraine",
      "percent": 15,
      "deckCount": 7136,
      "synergy": 5
    },
    {
      "name": "Commander's Sphere",
      "percent": null,
      "deckCount": null,
      "synergy": null
    },
    {
      "name": "Extraplanar Lens",
      "percent": 9,
      "deckCount": 7136,
      "synergy": 1
    },
    {
      "name": "Caged Sun",
      "percent": null,
      "deckCount": null,
      "synergy": null
    },
    {
      "name": "Decanter of Endless Water",
      "percent": null,
      "deckCount": null,
      "synergy": null
    },
    {
      "name": "Sceptre of Eternal Glory",
      "percent": 7,
      "deckCount": 7136,
      "synergy": 3
    },
    {
      "name": "Nyx Lotus",
      "percent": 7,
      "deckCount": 7136,
      "synergy": 2
    },
    {
      "name": "Misleading Signpost",
      "percent": 7,
      "deckCount": 7136,
      "synergy": 2
    },
    {
      "name": "Gilded Lotus",
      "percent": null,
      "deckCount": null,
      "synergy": null
    },
    {
      "name": "Thran Dynamo",
      "percent": null,
      "deckCount": null,
      "synergy": null
    },
    {
      "name": "Island",
      "percent": 96,
      "deckCount": 7136,
      "synergy": 3
    },
    {
      "name": "Myriad Landscape",
      "percent": 29,
      "deckCount": 7136,
      "synergy": 2
    },
    {
      "name": "Hydroelectric Specimen",
      "percent": 18,
      "deckCount": 7136,
      "synergy": 5
    },
    {
      "name": "Sink into Stupor",
      "percent": null,
      "deckCount": null,
      "synergy": null
    },
    {
      "name": "Command Tower",
      "percent": 10,
      "deckCount": 7136,
      "synergy": 6
    },
    {
      "name": "Sea Gate Restoration",
      "percent": null,
      "deckCount": null,
      "synergy": null
    },
    {
      "name": "Evolving Wilds",
      "percent": 5,
      "deckCount": 7136,
      "synergy": 2
    }
  ]
}